skg/__init__.py
skg/_util.py
skg/exp.py
skg/gauss.py
skg/gauss_cdf.py
skg/gauss_pdf.py
skg/ngauss.py
skg/nsphere.py
skg/pow.py
skg/version.py
skg/weibull_cdf.py
skg/tests/__init__.py
skg/tests/conftest.py
skg/tests/noise.py
skg/tests/options.py
skg/tests/test_exp.py
skg/tests/test_gauss_cdf.py
skg/tests/test_gauss_pdf.py
skg/tests/test_nsphere.py
skg/tests/test_pow.py
skg/tests/test_weibull_cdf.py
skg/tests/timing.py
skg/tests/util.py
scikit_guess-0.0.1a0.dist-info/LICENSE
scikit_guess-0.0.1a0.dist-info/METADATA
scikit_guess-0.0.1a0.dist-info/WHEEL
scikit_guess-0.0.1a0.dist-info/top_level.txt
scikit_guess-0.0.1a0.dist-info/RECORD
